midgard_discord/__init__.py
midgard_discord/cloud.py
midgard_discord/commands.py
midgard_discord/database.py
midgard_discord/main.py
midgard_discord/networking.py
midgard_discord/texts.py
midgard_discord/utils.py
midgard_discord-0.8.0.dist-info/METADATA
midgard_discord-0.8.0.dist-info/WHEEL
midgard_discord-0.8.0.dist-info/entry_points.txt
midgard_discord-0.8.0.dist-info/RECORD
