Metadata-Version: 2.1
Name: midgard-discord
Version: 0.8.0
Summary: ChatOps discord bot to request and provision Openstack resources in MidgardLab
Author: Nhat Ngo
Author-email: discordbot.awg4s@mail.ngo.cx
Requires-Python: >=3.10,<4.0
Classifier: Programming Language :: Python :: 3
Classifier: Programming Language :: Python :: 3.10
Classifier: Programming Language :: Python :: 3.11
Requires-Dist: aiohttp (>=3.8.4,<4.0.0)
Requires-Dist: aiosqlite (>=0.18.0,<0.19.0)
Requires-Dist: discord-py-interactions (>=4.4,<5.0)
Requires-Dist: openstacksdk (>=1.0.1,<2.0.0)
Requires-Dist: python-dotenv (>=1.0.0,<2.0.0)
Requires-Dist: sqlalchemy[asyncio] (>=2.0.9,<3.0.0)
